simple_processor/verilog/pc.v
/*
- Simple 4-bit program counter
- Increments every clock cycle
- Resets to 0 on reset
*/

module pc (
    input  wire       clk,
    input  wire       reset,
    output reg  [3:0] pc_out
);

    always @(posedge clk or posedge reset) begin
        if (reset)
            pc_out <= 4'd0;
        else
            pc_out <= pc_out + 4'd1;
    end

endmodule

simple_processor/verilog/data_memory.v
/*
- data_memory.v
- 8-bit wide, 16-word data memory
- Supports synchronous write and asynchronous read

*/

module data_memory(
    input wire clk,
    input wire write_en, //write enable
    input wire [3:0] addr, // write address
    input wire [7:0] write_data, //write data
    output wire [7:0] read_data 
);
    
    //16 x 8bit memory
    reg [7:0] mem [0:15];

    //Load contents from the file
    initial $readmemh("F:/processor_design/simple_processor/perceptron_model/data.hex", mem);

    // Asynchronous read
    assign read_data = mem[addr];

    // Synchronous write
    always @(posedge clk) begin
        if (write_en) begin
            mem[addr] <= write_data;
        end
    end
endmodule

simple_processor/verilog/alu.v
/*
- ALU: Arithmetic Logic Unit for custom ML processor
- Supports operations: NOP, ADD, MUL, ACT (step function)
*/


module alu(
    input wire [7:0] op1,
    input wire [7:0] op2,
    input wire [2:0] alu_ctrl,
    output reg [7:0] result
);

    always @(*) begin
        case (alu_ctrl)
        3'b000: result = op1; // pass through
        3'b001: result = op1 + op2; // ADD 
        3'b010: result = op1 * op2; // MUL 
        3'b011: result = (op1>0) ? 8'd1 :8'd0 ;// ACT : outputs 1 if input > 0, else 0
        default: result =8'd0;
        endcase
    end
endmodule

simple_processor/verilog/register_file.v
/*
- Register file is a small memory block used to store the intermidate values during execution.
- Registers are noting but a group of flipflops. 
- The registers designed here will be synthesised as D Flipflops as
    - it is written inside a synchronous always block
    - updated on clock edges
- !! Not to be confused with 'reg' in Verilog. 
- the 'reg' in verilog is just a variable that can hold a value

- From the instruction_memory.v file, we have used 8 registers
- Each register is 8 bit wide 
- The register file should support 
    - Two simultananeous reads
    - one write
- Why do we go with two reads and one write is because 
    - Operations like:
        - ADD R4, R2, R3 → R4 = R2 + R3
        - MUL R2, R0, R1 → R2 = R0 × R1
    - Need:
        - 2 source operands (e.g., R0, R1)
        - 1 destination (e.g., R2)
    - So:
        - You must read 2 registers in the same clock cycle
        - You must write 1 result at the end of that cycle

Also, This matches most common CPU Architectures

| Architecture | Register File Ports |
| ------------ | ------------------- |
| MIPS         | 2 read, 1 write     |
| RISC-V       | 2 read, 1 write     |
| ARM          | 2 read, 1 write     |

*/

module register_file(
    input wire clk,

    //instantiate variables for write operation
    input wire we, //write enable
    input wire [2:0] wr_addr, //write address
    input wire [7:0] wr_data, //write data

    //instantiate variables for read operation
    // it is done twice because of 2 reads 
    input wire rd, //read enable
    input wire [2:0] rd_addr1, //read address 1
    input wire [2:0] rd_addr2, //read address 2
    
    // output wire and not input because the data has to be read out 
    
    output wire [7:0] rd_data1, //read data 1
    output wire [7:0] rd_data2 // read data 2
);

// we need 8 registers each of size 8 bit
// reg [7:0] regs - this tells that regs is 8 bit wide
// reg [7:0] regs [0:7] - this tells that there are 8 registers from 0 to 7 each 8b wide

    reg [7:0] regs [0:7];

    // To read the values from the registers we need the values to be present in it
    // The registers must have the values updated in the same cycle before ALU executes the operation
    // Thus we use asynchronous read.

    assign rd_data1 = regs[rd_addr1];
    assign rd_data2 = regs[rd_addr2];

    // Writing is a state-changing operation — so it must be:
    //    - Controlled, Predictable & Aligned with instruction timing
    // Synchronous write ensures:
    //    - Only one value is written per clock cycle
    //    - No race conditions occur
    //    - Works correctly with the write enable (we) and pipeline control
    always@(posedge clk)begin 
        if (we) begin 
            regs[wr_addr] <= wr_data;
        end
    end

endmodule

simple_processor/verilog/datapath.v
/*
The datapath is used to
- Wires together register file, ALU, data memory
- Execute the operation specified by opcode + control signals

The datapath receives:
    -The instruction (split into opcode and operand)
    -The control signals (from the control unit)
    -Clock and reset signals

It manages:
    - Reading from registers
    - Performing ALU operations
    - Accessing data memory
    - Writing back results to registers or memory

*/

module datapath (
    input  wire        clk,
    input  wire [3:0]  opcode,
    input  wire [3:0]  operand,
    input  wire [2:0]  alu_ctrl,
    input  wire        reg_we,
    input  wire        mem_we,

    output wire [7:0]  mem_read_data  // for external observation
);

    // Split operand into subfields
    wire [2:0] rs1 = operand[3:2];  // source register 1
    wire [2:0] rs2 = operand[1:0];  // source register 2
    wire [2:0] rd  = operand[3:1];  // dest register (for example)

    // Register file wires
    wire [7:0] reg_out1;
    wire [7:0] reg_out2;
    wire [7:0] reg_write_data;

    // ALU output
    wire [7:0] alu_result;

    // Data memory output
    wire [7:0] data_out;

    // Instantiate Register File
    register_file regfile (
        .clk(clk),
        .we(reg_we),
        .wr_addr(rd),
        .wr_data(reg_write_data),
        .rd_addr1(rs1),
        .rd_addr2(rs2),
        .rd_data1(reg_out1),
        .rd_data2(reg_out2)
    );

    // Instantiate ALU
    alu alu_unit (
        .op1(reg_out1),
        .op2(reg_out2),
        .alu_ctrl(alu_ctrl),
        .result(alu_result)
    );

    // Instantiate Data Memory
    data_memory mem (
        .clk(clk),
        .write_en(mem_we),
        .addr(operand[3:0]),
        .write_data(reg_out1),
        .read_data(data_out)
    );

    // Result routing logic
    // For LOAD: use data memory output
    // For ALU ops: use alu_result
    assign reg_write_data = (opcode == 4'b0000) ? data_out : alu_result;
    assign mem_read_data  = data_out;

endmodule

simple_processor/verilog/control_unit.v
/*
The control unit is the part of the processor that interprets instructions and 
generates the necessary control signals to execute them.
It is essentially the decision-maker in your CPU.

- It decodes the opcode (0000, 0010 etc from the instruction memeory) 
- extracts the operand address (last 4 bits from the instruction memory on where to store what)
- Outputs the control (to ALU, register file, the data memory or the write back logic)
*/
/*
- control.v
- Decodes the 8-bit instruction and generates control signals
*/

module control (
    input  wire [7:0] instr,        // Full 8-bit instruction

    output wire [3:0] opcode,       // Upper 4 bits of instr
    output wire [3:0] operand,      // Lower 4 bits of instr

    output reg  [2:0] alu_ctrl,     // ALU operation selector
    output reg        reg_we,       // Register write enable
    output reg        mem_we        // Data memory write enable
    );

    // Split instruction into opcode and operand
    assign opcode  = instr[7:4];
    assign operand = instr[3:0];

    // Generate control signals based on opcode
    always @(*) begin
        // Default values
        alu_ctrl = 3'b000; // NOP
        reg_we   = 1'b0;
        mem_we   = 1'b0;

        case (instr[7:4])
            4'b0000: begin // LOAD
                alu_ctrl = 3'b000; // NOP / passthrough
                reg_we   = 1'b1;
            end

            4'b0001: begin // STORE
                alu_ctrl = 3'b000;
                mem_we   = 1'b1;
            end

            4'b0010: begin // MUL
                alu_ctrl = 3'b010;
                reg_we   = 1'b1;
            end

            4'b0100: begin // ADD
                alu_ctrl = 3'b001;
                reg_we   = 1'b1;
            end

            4'b0110: begin // ACT (step)
                alu_ctrl = 3'b011;
                reg_we   = 1'b1;
            end

            4'b1111: begin // NOP / HALT
                alu_ctrl = 3'b000;
            end

            default: begin
                alu_ctrl = 3'b000;
            end
        endcase
    end

endmodule

simple_processor/verilog/instruction_memory.v
/*
- Instruction memory stores the program that the processor will execute.
- To understand the working, we consider this as ROM 

- ROM - Read only memory
- ROM is not writable at runtime and is hardcoded during design.
- Instructions here are written as case statements

- For this ROM design, there is one input and one output
- Input is the 4bit address of where to pick the instruction
- Output is an 8bit instruction
    - The split up of 8-bit wide instructions will be as 
    - [7:4] - op code (instr. address)
    - [3:2] - destination registers 
    - [1:0] - source registers (memory address)

- The 16-word indicates that it can hold a maximum of 16 instructions
- Since the input address is 4 bit wide, the processer can access 2pow4 = 16 memory locations

To set up the instrcutions the opcode, the oprands, instruction and operation is as follows


| Opcode  | Binary | Hex | Operands Format  | Instruction         | Operation                           |
| ------- | ------ | --- | ---------------- | ------------------- | ----------------------------------- |
| `LOAD`  | `0000` | 0x0 | `[Reg, MemAddr]` | `LOAD Rr, [Maddr]`  | `Rr ← MEM[Maddr]`                   |
| `STORE` | `0001` | 0x1 | `[Reg, MemAddr]` | `STORE Rr, [Maddr]` | `MEM[Maddr] ← Rr`                   |
| `MUL`   | `0010` | 0x2 | `[Rd, Rs]`       | `MUL Rd, Rs`        | `Rd ← Rd × Rs`                      |
| `MAC`   | `0011` | 0x3 | `[Rd, Rs]`       | `MAC Rd, Rs`        | `Rd ← Rd + (Rd × Rs)` *(optional)*  |
| `ADD`   | `0100` | 0x4 | `[Rd, Rs]`       | `ADD Rd, Rs`        | `Rd ← Rd + Rs`                      |
| `SUB`   | `0101` | 0x5 | `[Rd, Rs]`       | `SUB Rd, Rs`        | `Rd ← Rd - Rs` *(optional)*         |
| `ACT`   | `0110` | 0x6 | `[Rd]`           | `ACT Rd`            | `Rd ← step(Rd)`                     |
| `CMP`   | `0111` | 0x7 | `[R1, R2]`       | `CMP R1, R2`        | `ZF ← (R1 == R2)` *(optional)*      |
| `JMP`   | `1000` | 0x8 | `[Addr]`         | `JMP Addr`          | `PC ← Addr` *(optional)*            |
| `BEQ`   | `1001` | 0x9 | `[Addr]`         | `BEQ Addr`          | `PC ← Addr if ZF == 1` *(optional)* |
| `NOP`   | `1110` | 0xE | —                | `NOP`               | No operation                        |
| `HALT`  | `1111` | 0xF | —                | `HALT`              | Stop execution                      |


*/


module instruction_memory(
    input wire [3:0] addr,
    output reg [7:0] instruction
);

    always @(*) begin
        case (addr)
            //addr : instruction = 8'b[Opcode + Operands];
            4'd0: instruction = 8'b00000000 ; // LOAD R0, MEM[0]
            4'd1: instruction = 8'b00000001 ; // LOAD R1, MEM[1]
            4'd2: instruction = 8'b01000001 ; // MUL R2= R0*R1 
            4'd3: instruction = 8'b00000010 ; // LOAD R0, MEM[2]
            4'd4: instruction = 8'b00000011 ; // LOAD R1, MEM[3]
            4'd5: instruction = 8'b00110001 ; // MUL R3 = R0*R1
            4'd6: instruction = 8'b01000110 ; // ADD R4 = R2 + R3
            4'd7: instruction = 8'b00000100; // LOAD R0, MEM[4]
            4'd8: instruction = 8'b01010000; // ADD R5 = R4 + R0
            4'd9: instruction = 8'b01100000; // ACT R6 = step(R5)
            4'd10: instruction = 8'b00011101; // STORE R6, MEM[13]
            default: instruction = 8'b11110000; // NOP or HALT
        endcase     
    end
endmodule

simple_processor/verilog/top.v
/*
- top.v
- Top-level processor module
- Integrates PC, instruction memory, control unit, and datapath
*/

module top (
    input wire clk,
    input wire reset,

    output wire [7:0] mem_read_data  // Final output (e.g., classification result)
);

    // 4-bit Program Counter (can address 16 instructions)
    wire [3:0] pc;

    // Instruction fetched from ROM
    wire [7:0] instr;

    // Decoded fields
    wire [3:0] opcode;
    wire [3:0] operand;

    // Control signals
    wire [2:0] alu_ctrl;
    wire       reg_we;
    wire       mem_we;

    // Instruction Memory
    instruction_memory imem (
        .addr(pc),
        .instruction(instr)
    );

    // Control Unit
    control cu (
        .instr(instr),
        .opcode(opcode),
        .operand(operand),
        .alu_ctrl(alu_ctrl),
        .reg_we(reg_we),
        .mem_we(mem_we)
    );

    // Datapath
    datapath dp (
        .clk(clk),
        .opcode(opcode),
        .operand(operand),
        .alu_ctrl(alu_ctrl),
        .reg_we(reg_we),
        .mem_we(mem_we),
        .mem_read_data(mem_read_data)
    );


    pc pc_inst (
        .clk(clk),
        .reset(reset),
        .pc_out(pc)
);


endmodule

simple_processor/verilog/top_tb.v
`timescale 1ns/1ps

module top_tb;
    initial begin
        $dumpfile("wave.vcd");
        $dumpvars(0, top_tb);
    end

    reg clk;
    reg reset;
    wire [7:0] mem_read_data;

    // Instantiate the processor
    top uut (
        .clk(clk),
        .reset(reset),
        .mem_read_data(mem_read_data)
    );

    // Clock generation
    always #5 clk = ~clk;

    initial begin
        // Initialize
        clk = 0;
        reset = 1;

        // Apply reset
        #10 reset = 0;

        // Run for 200 ns (20 cycles)
        #200;
        
        $display("Final Output (Classification): %d", mem_read_data);
        $finish;
    end
    $display("Memory[13] = %d", uut.dp.mem.mem[13]);

endmodule

simple_processor/verilog/wave.vcd
$date
	Tue Jul 01 19:48:40 2025
$end
$version
	Icarus Verilog
$end
$timescale
	1ps
$end
$scope module top_tb $end
$var wire 8 ! mem_read_data [7:0] $end
$var reg 1 " clk $end
$var reg 1 # reset $end
$scope module uut $end
$var wire 1 " clk $end
$var wire 1 # reset $end
$var wire 1 $ reg_we $end
$var wire 4 % pc [3:0] $end
$var wire 4 & operand [3:0] $end
$var wire 4 ' opcode [3:0] $end
$var wire 1 ( mem_we $end
$var wire 8 ) mem_read_data [7:0] $end
$var wire 8 * instr [7:0] $end
$var wire 3 + alu_ctrl [2:0] $end
$scope module cu $end
$var wire 4 , operand [3:0] $end
$var wire 4 - opcode [3:0] $end
$var wire 8 . instr [7:0] $end
$var reg 3 / alu_ctrl [2:0] $end
$var reg 1 ( mem_we $end
$var reg 1 $ reg_we $end
$upscope $end
$scope module dp $end
$var wire 3 0 alu_ctrl [2:0] $end
$var wire 1 " clk $end
$var wire 8 1 mem_read_data [7:0] $end
$var wire 1 ( mem_we $end
$var wire 4 2 opcode [3:0] $end
$var wire 4 3 operand [3:0] $end
$var wire 1 $ reg_we $end
$var wire 3 4 rs2 [2:0] $end
$var wire 3 5 rs1 [2:0] $end
$var wire 8 6 reg_write_data [7:0] $end
$var wire 8 7 reg_out2 [7:0] $end
$var wire 8 8 reg_out1 [7:0] $end
$var wire 3 9 rd [2:0] $end
$var wire 8 : data_out [7:0] $end
$var wire 8 ; alu_result [7:0] $end
$scope module alu_unit $end
$var wire 3 < alu_ctrl [2:0] $end
$var wire 8 = op2 [7:0] $end
$var wire 8 > op1 [7:0] $end
$var reg 8 ? result [7:0] $end
$upscope $end
$scope module mem $end
$var wire 4 @ addr [3:0] $end
$var wire 1 " clk $end
$var wire 8 A read_data [7:0] $end
$var wire 1 ( write_en $end
$var wire 8 B write_data [7:0] $end
$upscope $end
$scope module regfile $end
$var wire 1 " clk $end
$var wire 1 C rd $end
$var wire 3 D rd_addr1 [2:0] $end
$var wire 3 E rd_addr2 [2:0] $end
$var wire 8 F rd_data1 [7:0] $end
$var wire 8 G rd_data2 [7:0] $end
$var wire 1 $ we $end
$var wire 3 H wr_addr [2:0] $end
$var wire 8 I wr_data [7:0] $end
$upscope $end
$upscope $end
$scope module imem $end
$var wire 4 J addr [3:0] $end
$var reg 8 K instruction [7:0] $end
$upscope $end
$scope module pc_inst $end
$var wire 1 " clk $end
$var wire 1 # reset $end
$var reg 4 L pc_out [3:0] $end
$upscope $end
$upscope $end
$upscope $end
$enddefinitions $end
$comment Show the parameter values. $end
$dumpall
$end
#0
$dumpvars
b0 L
b0 K
b0 J
b101 I
b0 H
bx G
bx F
b0 E
b0 D
zC
bx B
b101 A
b0 @
bx ?
bx >
bx =
b0 <
bx ;
b101 :
b0 9
bx 8
bx 7
b101 6
b0 5
b0 4
b0 3
b0 2
b101 1
b0 0
b0 /
b0 .
b0 -
b0 ,
b0 +
b0 *
b101 )
0(
b0 '
b0 &
b0 %
1$
1#
0"
b101 !
$end
#5000
b101 ;
b101 ?
b101 8
b101 >
b101 B
b101 F
b101 7
b101 =
b101 G
1"
#10000
0"
0#
#15000
bx 7
bx =
bx G
b1 4
b1 E
b10101 6
b10101 I
b10101 !
b10101 )
b10101 1
b10101 :
b10101 A
b1 &
b1 ,
b1 3
b1 @
1$
b1 *
b1 .
b1 K
b1 %
b1 J
b1 L
1"
#20000
0"
#25000
bx 6
bx I
b100 '
b100 -
b100 2
b1 +
b1 /
b1 0
b1 <
1$
bx ;
bx ?
b1000001 *
b1000001 .
b1000001 K
b10101 8
b10101 >
b10101 B
b10101 F
b10 %
b10 J
b10 L
1"
#30000
0"
#35000
b10 4
b10 E
b1 9
b1 H
b11 6
b11 I
b11 !
b11 )
b11 1
b11 :
b11 A
b10 &
b10 ,
b10 3
b10 @
b0 '
b0 -
b0 2
1$
b0 +
b0 /
b0 0
b0 <
b10 *
b10 .
b10 K
bx 8
bx >
bx B
bx F
b11 %
b11 J
b11 L
1"
#40000
0"
#45000
b11 4
b11 E
b11011100 6
b11011100 I
b11011100 !
b11011100 )
b11011100 1
b11011100 :
b11011100 A
b11 &
b11 ,
b11 3
b11 @
1$
b11 *
b11 .
b11 K
b100 %
b100 J
b100 L
1"
#50000
0"
#55000
b11011100 7
b11011100 =
b11011100 G
b1 4
b1 E
b0 9
b0 H
bx 6
bx I
b10101 !
b10101 )
b10101 1
b10101 :
b10101 A
b1 &
b1 ,
b1 3
b1 @
b11 '
b11 -
b11 2
0$
b110001 *
b110001 .
b110001 K
b101 %
b101 J
b101 L
1"
#60000
0"
#65000
b11011100 8
b11011100 >
b11011100 B
b11011100 F
b1 5
b1 D
bx 7
bx =
bx G
b10 4
b10 E
b11 9
b11 H
bx !
bx )
bx 1
bx :
bx A
b110 &
b110 ,
b110 3
b110 @
b100 '
b100 -
b100 2
1$
b1 +
b1 /
b1 0
b1 <
b1000110 *
b1000110 .
b1000110 K
b110 %
b110 J
b110 L
1"
#70000
0"
#75000
b0 4
b0 E
b10 9
b10 H
b11111011 6
b11111011 I
b11011100 ;
b11011100 ?
b11111011 !
b11111011 )
b11111011 1
b11111011 :
b11111011 A
b100 &
b100 ,
b100 3
b100 @
b0 '
b0 -
b0 2
1$
b0 +
b0 /
b0 0
b0 <
b100 *
b100 .
b100 K
b111 %
b111 J
b111 L
1"
#80000
0"
#85000
bx ;
bx ?
bx 8
bx >
bx B
bx F
b0 5
b0 D
b0 9
b0 H
bx 6
bx I
b101 !
b101 )
b101 1
b101 :
b101 A
b0 &
b0 ,
b0 3
b0 @
b101 '
b101 -
b101 2
0$
b1010000 *
b1010000 .
b1010000 K
b1000 %
b1000 J
b1000 L
1"
#90000
0"
#95000
b0x 6
b0x I
b0x ;
b0x ?
b110 '
b110 -
b110 2
1$
b11 +
b11 /
b11 0
b11 <
b1100000 *
b1100000 .
b1100000 K
b1001 %
b1001 J
b1001 L
1"
#100000
0"
#105000
bx 6
bx I
bx ;
bx ?
b11 5
b11 D
b1 4
b1 E
b110 9
b110 H
bx !
bx )
bx 1
bx :
bx A
b1101 &
b1101 ,
b1101 3
b1101 @
b1 '
b1 -
b1 2
1(
0$
b0 +
b0 /
b0 0
b0 <
b11101 *
b11101 .
b11101 K
bx 8
bx >
bx B
bx F
b11011100 7
b11011100 =
b11011100 G
b1010 %
b1010 J
b1010 L
1"
#110000
0"
#115000
b0x 6
b0x I
b0x ;
b0x ?
b0x 8
b0x >
b0x B
b0x F
b0 5
b0 D
b0x 7
b0x =
b0x G
b0 4
b0 E
b0 9
b0 H
b101 !
b101 )
b101 1
b101 :
b101 A
b0 &
b0 ,
b0 3
b0 @
b1111 '
b1111 -
b1111 2
0(
b11110000 *
b11110000 .
b11110000 K
b1011 %
b1011 J
b1011 L
1"
#120000
0"
#125000
b1100 %
b1100 J
b1100 L
1"
#130000
0"
#135000
b1101 %
b1101 J
b1101 L
1"
#140000
0"
#145000
b1110 %
b1110 J
b1110 L
1"
#150000
0"
#155000
b1111 %
b1111 J
b1111 L
1"
#160000
0"
#165000
b101 6
b101 I
b0 '
b0 -
b0 2
1$
b0 *
b0 .
b0 K
b0 %
b0 J
b0 L
1"
#170000
0"
#175000
b1 4
b1 E
b10101 6
b10101 I
b10101 !
b10101 )
b10101 1
b10101 :
b10101 A
b1 &
b1 ,
b1 3
b1 @
1$
b101 ;
b101 ?
b1 *
b1 .
b1 K
b101 8
b101 >
b101 B
b101 F
b11011100 7
b11011100 =
b11011100 G
b1 %
b1 J
b1 L
1"
#180000
0"
#185000
b11110001 6
b11110001 I
b100 '
b100 -
b100 2
b1 +
b1 /
b1 0
b1 <
1$
b11110001 ;
b11110001 ?
b1000001 *
b1000001 .
b1000001 K
b10101 8
b10101 >
b10101 B
b10101 F
b10 %
b10 J
b10 L
1"
#190000
0"
#195000
b11111011 7
b11111011 =
b11111011 G
b10 4
b10 E
b1 9
b1 H
b11 6
b11 I
b11 !
b11 )
b11 1
b11 :
b11 A
b10 &
b10 ,
b10 3
b10 @
b0 '
b0 -
b0 2
1$
b0 +
b0 /
b0 0
b0 <
b11110001 ;
b11110001 ?
b10 *
b10 .
b10 K
b11110001 8
b11110001 >
b11110001 B
b11110001 F
b11 %
b11 J
b11 L
1"
#200000
0"
#205000
bx 7
bx =
bx G
b11 4
b11 E
b11011100 6
b11011100 I
b11011100 !
b11011100 )
b11011100 1
b11011100 :
b11011100 A
b11 &
b11 ,
b11 3
b11 @
1$
b11 *
b11 .
b11 K
b100 %
b100 J
b100 L
1"
